{
  "$defs": {
    "MergePosition": {
      "description": "Controls where an overlay onDrift entry is placed relative to Origin-generated entries\nduring Asset overlay merge.",
      "enum": [
        "beforeOrigin",
        "afterOrigin"
      ],
      "type": "string"
    }
  },
  "$schema": "https://json-schema.org/draft/2020-12/schema",
  "description": "An entry in `on_drift`. Pairs a Conditions reference with a Sync reference.\nThe conditions are evaluated as a group (all must pass for no drift).",
  "properties": {
    "conditions": {
      "description": "Name of the `kind: Conditions` resource whose conditions define drift.",
      "type": "string"
    },
    "mergePosition": {
      "$ref": "#/$defs/MergePosition",
      "default": "beforeOrigin",
      "description": "Controls insertion position during overlay merge. Not included in compiled output."
    },
    "sync": {
      "description": "Name of the Sync resource to execute when drift is detected.",
      "type": "string"
    },
    "with": {
      "additionalProperties": {
        "type": "string"
      },
      "default": {},
      "description": "Template variables passed to the Sync and Conditions resources for argument interpolation.",
      "type": "object"
    }
  },
  "required": [
    "conditions",
    "sync"
  ],
  "title": "OnDriftEntry",
  "type": "object"
}